src/MotorControl.v
module MotorControl(input clk, input [1:0] direction, output reg left_pwm, output reg right_pwm);
    reg [7:0] pwm_counter;

    always @(posedge clk) begin
        pwm_counter <= pwm_counter + 1;

        case (direction)
            2'b00: begin
                left_pwm <= 0;
                right_pwm <= 0;
            end
            2'b01: begin
                left_pwm <= (pwm_counter < 128);  // Forward movement
                right_pwm <= (pwm_counter < 128);
            end
            2'b10: begin
                left_pwm <= 0;  // Turn left, stop left motor
                right_pwm <= (pwm_counter < 128);
            end
            2'b11: begin
                left_pwm <= (pwm_counter < 128);  // Turn right, stop right motor
                right_pwm <= 0;
            end
        endcase
    end
endmodule

src/RobotControl.v
module RobotControl(input clk, input [15:0] distance, output reg [1:0] direction);
    reg [1:0] state;
    parameter FORWARD = 2'b01, LEFT = 2'b10, RIGHT = 2'b11, STOP = 2'b00;

    always @(posedge clk) begin
        case (state)
            STOP: if (distance > 30) state <= FORWARD;
            FORWARD: if (distance < 30) state <= LEFT;
            LEFT: if (distance > 30) state <= FORWARD;
            default: state <= STOP;
        endcase
        direction <= state;
    end
endmodule

src/Sensor.v
module Sensor(input clk, input trigger, input echo, output reg [15:0] distance);
    reg [15:0] timer;

    always @(posedge clk) begin
        if (trigger) begin
            timer <= 0;  // Start timer
        end
        if (echo) begin
            timer <= timer + 1;  // Measure time while echo is high
        end
        distance <= timer * 58; // Convert to distance in cm
    end
endmodule

src/RobotTop.v
module RobotTop(input clk, input trigger, input echo, output left_pwm, output right_pwm);
    wire [15:0] distance;
    wire [1:0] direction;

    // Instantiate sensor, FSM, and motor control modules
    Sensor sensor(clk, trigger, echo, distance);
    RobotControl control(clk, distance, direction);
    MotorControl motor(clk, direction, left_pwm, right_pwm);
endmodule

tb/RobotTop_tb.v
module RobotTop_tb;
    reg clk, trigger, echo;
    wire left_pwm, right_pwm;

    // Instantiate the top module
    RobotTop uut(
        .clk(clk),
        .trigger(trigger),
        .echo(echo),
        .left_pwm(left_pwm),
        .right_pwm(right_pwm)
    );

    // Clock Generation
    initial begin
        clk = 0;
        forever #5 clk = ~clk;  // 10ns clock period
    end

    // Stimulus
    initial begin
        // Initialize
        trigger = 0;
        echo = 0;

        // Trigger sensor and simulate echo with varying distance
        #10 trigger = 1;  // Trigger ultrasonic sensor
        #20 echo = 1;     // Simulate echo pulse

        #50 echo = 0;     // Echo ends (distance is large, robot moves forward)
        #100 echo = 1;    // Obstacle closer, robot should turn
        #150 echo = 0;

        // Continue simulation
        #300 $finish;     // End simulation after 300 time units
    end

    // Dump waveform for analysis
    initial begin
        $dumpfile("robot_control.vcd");
        $dumpvars(0, RobotTop_tb);
    end
endmodule

robot_control.vcd
$date
	Sun Sep 15 11:52:55 2024
$end
$version
	Icarus Verilog
$end
$timescale
	1s
$end
$scope module RobotTop_tb $end
$var wire 1 ! right_pwm $end
$var wire 1 " left_pwm $end
$var reg 1 # clk $end
$var reg 1 $ echo $end
$var reg 1 % trigger $end
$scope module uut $end
$var wire 1 # clk $end
$var wire 1 $ echo $end
$var wire 1 % trigger $end
$var wire 1 ! right_pwm $end
$var wire 1 " left_pwm $end
$var wire 16 & distance [15:0] $end
$var wire 2 ' direction [1:0] $end
$scope module control $end
$var wire 1 # clk $end
$var wire 16 ( distance [15:0] $end
$var parameter 2 ) FORWARD $end
$var parameter 2 * LEFT $end
$var parameter 2 + RIGHT $end
$var parameter 2 , STOP $end
$var reg 2 - direction [1:0] $end
$var reg 2 . state [1:0] $end
$upscope $end
$scope module motor $end
$var wire 1 # clk $end
$var wire 2 / direction [1:0] $end
$var reg 1 " left_pwm $end
$var reg 8 0 pwm_counter [7:0] $end
$var reg 1 ! right_pwm $end
$upscope $end
$scope module sensor $end
$var wire 1 # clk $end
$var wire 1 $ echo $end
$var wire 1 % trigger $end
$var reg 16 1 distance [15:0] $end
$var reg 16 2 timer [15:0] $end
$upscope $end
$upscope $end
$upscope $end
$enddefinitions $end
$comment Show the parameter values. $end
$dumpall
b0 ,
b11 +
b10 *
b1 )
$end
#0
$dumpvars
bx 2
bx 1
bx 0
bx /
bx .
bx -
bx (
bx '
bx &
0%
0$
0#
x"
x!
$end
#5
b0 .
1#
#10
0#
1%
#15
b0 '
b0 -
b0 /
b0 2
1#
#20
0#
#25
b0 &
b0 (
b0 1
0!
0"
1#
#30
0#
1$
#35
b1 2
1#
#40
0#
#45
b111010 &
b111010 (
b111010 1
b10 2
1#
#50
0#
#55
b1 .
b1110100 &
b1110100 (
b1110100 1
b11 2
1#
#60
0#
#65
b10101110 &
b10101110 (
b10101110 1
b100 2
b1 '
b1 -
b1 /
1#
#70
0#
#75
x!
x"
b11101000 &
b11101000 (
b11101000 1
b101 2
1#
#80
0#
0$
#85
b100100010 &
b100100010 (
b100100010 1
b0 2
1#
#90
0#
#95
b0 &
b0 (
b0 1
1#
#100
0#
#105
b10 .
1#
#110
0#
#115
b10 '
b10 -
b10 /
1#
#120
0#
#125
0"
1#
#130
0#
#135
1#
#140
0#
#145
1#
#150
0#
#155
1#
#160
0#
#165
1#
#170
0#
#175
1#
#180
0#
1$
#185
b1 2
1#
#190
0#
#195
b111010 &
b111010 (
b111010 1
b10 2
1#
#200
0#
#205
b1110100 &
b1110100 (
b1110100 1
b11 2
b1 .
1#
#210
0#
#215
b1 '
b1 -
b1 /
b10101110 &
b10101110 (
b10101110 1
b100 2
1#
#220
0#
#225
b11101000 &
b11101000 (
b11101000 1
b101 2
x"
1#
#230
0#
#235
b100100010 &
b100100010 (
b100100010 1
b110 2
1#
#240
0#
#245
b101011100 &
b101011100 (
b101011100 1
b111 2
1#
#250
0#
#255
b110010110 &
b110010110 (
b110010110 1
b1000 2
1#
#260
0#
#265
b111010000 &
b111010000 (
b111010000 1
b1001 2
1#
#270
0#
#275
b1000001010 &
b1000001010 (
b1000001010 1
b1010 2
1#
#280
0#
#285
b1001000100 &
b1001000100 (
b1001000100 1
b1011 2
1#
#290
0#
#295
b1001111110 &
b1001111110 (
b1001111110 1
b1100 2
1#
#300
0#
#305
b1010111000 &
b1010111000 (
b1010111000 1
b1101 2
1#
#310
0#
#315
b1011110010 &
b1011110010 (
b1011110010 1
b1110 2
1#
#320
0#
#325
b1100101100 &
b1100101100 (
b1100101100 1
b1111 2
1#
#330
0#
0$
#335
b1101100110 &
b1101100110 (
b1101100110 1
b0 2
1#
#340
0#
#345
b0 &
b0 (
b0 1
1#
#350
0#
#355
b10 .
1#
#360
0#
#365
b10 '
b10 -
b10 /
1#
#370
0#
#375
0"
1#
